qmigrator/__init__.py
qmigrator/migrations/__init__.py
qmigrator/migrations/csp_user.py
qmigrator/migrations/utils.py
q_migrator-1.0.3.dist-info/METADATA
q_migrator-1.0.3.dist-info/WHEEL
q_migrator-1.0.3.dist-info/entry_points.txt
q_migrator-1.0.3.dist-info/top_level.txt
q_migrator-1.0.3.dist-info/RECORD
