Metadata-Version: 2.4
Name: q-migrator
Version: 1.0.3
Summary: Cufit-C 마이그레이션 툴
Author-email: Seungsu Hwang <h970126@gmail.com>
License: MIT
Requires-Python: >=3.9
Requires-Dist: typer>=0.9
Requires-Dist: sqlalchemy>=2.0
Requires-Dist: pandas
Requires-Dist: openpyxl
